Snipe_Bot_Argyraspide/__init__.py
Snipe_Bot_Argyraspide/config.py
Snipe_Bot_Argyraspide/main.py
snipe_bot_argyraspide-0.0.4.dist-info/METADATA
snipe_bot_argyraspide-0.0.4.dist-info/WHEEL
snipe_bot_argyraspide-0.0.4.dist-info/RECORD
