Metadata-Version: 2.4
Name: Snipe_Bot_Argyraspide
Version: 0.0.4
Summary: A small twitch chatbot producing countdowns, see Readme for more info
Author-email:  Argyraspide <louisonbost@gmail.com>
License-Expression: CC-BY-NC-SA-2.0-FR
Classifier: Operating System :: OS Independent
Classifier: Programming Language :: Python :: 3
Requires-Python: >=3.11
Requires-Dist: twitchapi
